CHANGES.rst
LICENCE.GPL
LICENCE.rst
MANIFEST.in
README.rst
setup.cfg
setup.py
fourdigits/__init__.py
fourdigits.remotemembrane.egg-info/PKG-INFO
fourdigits.remotemembrane.egg-info/SOURCES.txt
fourdigits.remotemembrane.egg-info/dependency_links.txt
fourdigits.remotemembrane.egg-info/entry_points.txt
fourdigits.remotemembrane.egg-info/namespace_packages.txt
fourdigits.remotemembrane.egg-info/not-zip-safe
fourdigits.remotemembrane.egg-info/paster_plugins.txt
fourdigits.remotemembrane.egg-info/requires.txt
fourdigits.remotemembrane.egg-info/top_level.txt
fourdigits/remotemembrane/__init__.py
fourdigits/remotemembrane/configure.zcml
fourdigits/remotemembrane/interfaces.py
fourdigits/remotemembrane/tests.py
fourdigits/remotemembrane/browser/__init__.py
fourdigits/remotemembrane/browser/browser.py
fourdigits/remotemembrane/browser/configure.zcml
fourdigits/remotemembrane/browser/templates/addgroupmanager.zpt
fourdigits/remotemembrane/browser/templates/addpropertymanager.zpt
fourdigits/remotemembrane/browser/templates/addrolemanager.zpt
fourdigits/remotemembrane/browser/templates/adduserfactory.zpt
fourdigits/remotemembrane/browser/templates/addusermanager.zpt
fourdigits/remotemembrane/plugins/__init__.py
fourdigits/remotemembrane/plugins/configure.zcml
fourdigits/remotemembrane/plugins/groupmanager.py
fourdigits/remotemembrane/plugins/propertymanager.py
fourdigits/remotemembrane/plugins/rolemanager.py
fourdigits/remotemembrane/plugins/userfactory.py
fourdigits/remotemembrane/plugins/usermanager.py