Metadata-Version: 1.0
Name: fourdigits.remotemembrane
Version: 0.3
Summary: A set of PAS plugins so users
Home-page: http://www.fourdigits.nl
Author: Four Digits
Author-email: info@fourdigits.nl
License: GPL version 2
Platform: UNKNOWN
Classifier: Framework :: Plone
Classifier: Programming Language :: Python
